confusion/__init__.py
88AB6720D79B4CBD93CAB7180920D89C-1.5.dist-info/METADATA
88AB6720D79B4CBD93CAB7180920D89C-1.5.dist-info/WHEEL
88AB6720D79B4CBD93CAB7180920D89C-1.5.dist-info/top_level.txt
88AB6720D79B4CBD93CAB7180920D89C-1.5.dist-info/RECORD
