Metadata-Version: 2.1
Name: 88AB6720D79B4CBD93CAB7180920D89C
Version: 1.5
Summary: i am confused
Home-page: UNKNOWN
Author: Someone Confused
Author-email: someone@consused.example
License: UNKNOWN
Platform: UNKNOWN
